LIMBR/__init__.py
LIMBR/batch_fx.py
LIMBR/imputation.py
LIMBR/old_fashioned.py
LIMBR/simulations.py
LIMBR-0.2.10.dist-info/METADATA
LIMBR-0.2.10.dist-info/RECORD
LIMBR-0.2.10.dist-info/WHEEL
LIMBR-0.2.10.dist-info/top_level.txt
