Metadata-Version: 2.1
Name: LIMBR
Version: 0.2.10
Summary: Learning and Imputation for Mass-spec Bias Reduction
Home-page: https://github.com/aleccrowell/LIMBR
Author: Alec Crowell
Author-email: alexander.m.crowell@gmail.com
License: BSD-3
Download-URL: https://github.com/aleccrowell/LIMBR/releases/tag/v0.2.10
Keywords: SVA,SVD,mass-spec,bioinformatics
Platform: UNKNOWN
Requires-Dist: numpy
Requires-Dist: pandas
Requires-Dist: scipy
Requires-Dist: sklearn
Requires-Dist: statsmodels
Requires-Dist: tqdm
Requires-Dist: multiprocess
Requires-Dist: matplotlib
